fulcra_api/__init__.py
fulcra_api/core.py
fulcra_api-0.1.28.dist-info/METADATA
fulcra_api-0.1.28.dist-info/WHEEL
fulcra_api-0.1.28.dist-info/licenses/LICENSE
fulcra_api-0.1.28.dist-info/RECORD
