Metadata-Version: 2.4
Name: fulcra-api
Version: 0.1.28
Summary: 
License-File: LICENSE
Author: Brandon Creighton
Author-email: brandon@fulcradynamics.com
Requires-Python: >=3.11,<4.0
Classifier: Programming Language :: Python :: 3
Classifier: Programming Language :: Python :: 3.11
Classifier: Programming Language :: Python :: 3.12
Classifier: Programming Language :: Python :: 3.13
Classifier: Programming Language :: Python :: 3.14
Requires-Dist: numpy (>=2.0.0,<3.0.0)
Requires-Dist: pandas (>1.5,<3)
Requires-Dist: pyarrow (>=19.0.0)
